{
  "appId": "com.evmwallet.desktop",
  "productName": "EVM Wallet",
  "directories": {
    "output": "release",
    "buildResources": "assets"
  },
  "files": [
    "dist/**/*"
  ],
  "win": {
    "target": [
      {
        "target": "nsis",
        "arch": ["x64"]
      }
    ],
    "icon": "assets/icon.ico",
    "verifyUpdateCodeSignature": false
  },
  "nsis": {
    "oneClick": false,
    "allowToChangeInstallationDirectory": true,
    "createDesktopShortcut": true,
    "createStartMenuShortcut": true
  },
  "forceCodeSigning": false,
  "publish": {
    "provider": "github",
    "owner": "alexander-shmidt14",
    "repo": "EVM-wallet",
    "private": false
  }
}
